ctypedffi/__init__.py
ctypedffi/_metadata.py
ctypedffi/ctypes.py
ctypedffi/cython.py
ctypedffi/library.py
ctypedffi/py.typed
ctypedffi/string.py
ctypedffi/struct.py
ctypedffi/types.py
ctypedffi/utils.py
ctypedffi/libs/__init__.py
ctypedffi/libs/py_capsule.py
ctypedffi-1.2.0.dist-info/LICENSE
ctypedffi-1.2.0.dist-info/METADATA
ctypedffi-1.2.0.dist-info/WHEEL
ctypedffi-1.2.0.dist-info/top_level.txt
ctypedffi-1.2.0.dist-info/RECORD
