Metadata-Version: 2.1
Name: ctypedffi
Version: 1.2.0
Summary: Wrapper around ctypes, for creating typed foreign function libraries
Author: Setsugen no ao
Author-email: setsugen@setsugen.dev
Maintainer: Setsugen no ao
Maintainer-email: setsugen@setsugen.dev
Project-URL: Source Code, https://github.com/Setsugennoao/ctyped-ffi
Project-URL: Documentation, https://ctypedffi.encode.moe/en/latest/
Project-URL: Contact, https://discord.gg/qxTxVJGtst
Classifier: Programming Language :: Python :: 3
Classifier: License :: OSI Approved :: MIT License
Classifier: Operating System :: OS Independent
Requires-Python: >=3.12
License-File: LICENSE
Requires-Dist: ctypesgen ==1.1.1
